changelogdir.py
changelogdir-3.1.0.dist-info/DESCRIPTION.rst
changelogdir-3.1.0.dist-info/METADATA
changelogdir-3.1.0.dist-info/RECORD
changelogdir-3.1.0.dist-info/WHEEL
changelogdir-3.1.0.dist-info/entry_points.txt
changelogdir-3.1.0.dist-info/metadata.json
changelogdir-3.1.0.dist-info/top_level.txt
